multiprefixspan.py
multiprefixspan-0.0.2.dist-info/LICENSE
multiprefixspan-0.0.2.dist-info/METADATA
multiprefixspan-0.0.2.dist-info/WHEEL
multiprefixspan-0.0.2.dist-info/top_level.txt
multiprefixspan-0.0.2.dist-info/RECORD
